pypomes_messaging/__init__.py
pypomes_messaging/mq_config.py
pypomes_messaging/mq_publisher.py
pypomes_messaging/mq_subscriber.py
pypomes_messaging/publisher_pomes.py
pypomes_messaging/subscriber_pomes.py
pypomes_messaging-0.3.2.dist-info/METADATA
pypomes_messaging-0.3.2.dist-info/WHEEL
pypomes_messaging-0.3.2.dist-info/licenses/LICENSE
pypomes_messaging-0.3.2.dist-info/RECORD
