Metadata-Version: 2.4
Name: pypomes_messaging
Version: 0.3.2
Summary: A collection of Python pomes, penyeach (message handling modules)
Project-URL: Homepage, https://github.com/TheWiseCoder/PyPomes-Messaging
Project-URL: Bug Tracker, https://github.com/TheWiseCoder/PyPomes-Messaging/issues
Author-email: GT Nunes <wisecoder01@gmail.com>
License-File: LICENSE
Classifier: License :: OSI Approved :: MIT License
Classifier: Operating System :: OS Independent
Classifier: Programming Language :: Python :: 3
Requires-Python: >=3.14
Requires-Dist: pika>=1.3.2
Requires-Dist: pypomes-core>=2.9.4
